setup.cfg
setup.py
nebooman/__init__.py
nebooman/manager.py
nebooman.egg-info/PKG-INFO
nebooman.egg-info/SOURCES.txt
nebooman.egg-info/dependency_links.txt
nebooman.egg-info/top_level.txt
scripts/nebooman