Metadata-Version: 1.1
Name: nebooman
Version: 0.1
Summary: Netscape Bookmark Manager
Home-page: https://github.com/zebradil/nebooman
Author: German Lashevich
Author-email: german.lashevich@gmail.com
License: MIT
Download-URL: https://github.com/zebradil/nebooman/tarball/0.1
Keywords: netscape bookmark manager
Platform: UNKNOWN
Classifier: Environment :: Console
Classifier: Intended Audience :: Developers
Classifier: License :: OSI Approved :: MIT License
Classifier: Topic :: Terminals
